resteasycli/__init__.py
resteasycli/exceptions.py
resteasycli/cmd/__init__.py
resteasycli/cmd/common.py
resteasycli/cmd/doc.py
resteasycli/cmd/generic_request.py
resteasycli/cmd/initialize.py
resteasycli/cmd/main.py
resteasycli/cmd/request_factory.py
resteasycli/cmd/requests.py
resteasycli/cmd/workspace.py
resteasycli/config/__init__.py
resteasycli/config/default.py
resteasycli/config/parser.py
resteasycli/config/template.py
resteasycli/lib/__init__.py
resteasycli/lib/abstract_finder.py
resteasycli/lib/abstract_reader.py
resteasycli/lib/abstract_writer.py
resteasycli/lib/auth.py
resteasycli/lib/doc.py
resteasycli/lib/endpoint.py
resteasycli/lib/headers.py
resteasycli/lib/locked_read_writer.py
resteasycli/lib/request.py
resteasycli/lib/saved_request.py
resteasycli/lib/site.py
resteasycli/lib/utils.py
resteasycli/lib/workspace.py
resteasycli/schema/__init__.py
resteasycli/schema/auth.py
resteasycli/schema/common.py
resteasycli/schema/headers.py
resteasycli/schema/saved_requests.py
resteasycli/schema/sites.py
resteasycli/schema/workspace.py
RESTEasyCLI-0.9.8.dist-info/LICENSE
RESTEasyCLI-0.9.8.dist-info/METADATA
RESTEasyCLI-0.9.8.dist-info/WHEEL
RESTEasyCLI-0.9.8.dist-info/entry_points.txt
RESTEasyCLI-0.9.8.dist-info/top_level.txt
RESTEasyCLI-0.9.8.dist-info/RECORD
