Metadata-Version: 2.1
Name: RESTEasyCLI
Version: 0.9.8
Summary: Handy REST API client on your terminal
Home-page: https://github.com/rapidstack/RESTEasyCLI
Author: Arijit Basu
Author-email: sayanarijit@gmail.com
License: MIT
Download-URL: https://github.com/rapidstack/RESTEasyCLI/archive/v0.9.8.tar.gz
Keywords: REST API client CLI tool
Platform: Any
Classifier: Development Status :: 3 - Alpha
Classifier: Intended Audience :: Developers
Classifier: Intended Audience :: Information Technology
Classifier: License :: OSI Approved :: MIT License
Classifier: Natural Language :: English
Classifier: Programming Language :: Python :: 3.3
Classifier: Programming Language :: Python :: 3.4
Classifier: Programming Language :: Python :: 3.5
Classifier: Programming Language :: Python :: 3.6
Classifier: Programming Language :: Python :: 3.7
Classifier: Topic :: Internet
Classifier: Topic :: Utilities
Classifier: Topic :: Software Development
Classifier: Operating System :: MacOS
Classifier: Operating System :: Unix
Classifier: Operating System :: POSIX
Classifier: Operating System :: Microsoft
Requires-Dist: cliff (==2.14.1)
Requires-Dist: PyYAML (==5.1b5)
Requires-Dist: RESTEasy (==1.0.5)
Requires-Dist: marshmallow (==3.0.0rc4)
Requires-Dist: toml (==0.10.0)
Requires-Dist: Docify (==0.4.0)
Provides-Extra: develop
Requires-Dist: pip (==19.0.3) ; extra == 'develop'
Requires-Dist: setuptools (==40.8.0) ; extra == 'develop'
Requires-Dist: wheel (==0.33.1) ; extra == 'develop'
Requires-Dist: twine (==1.13.0) ; extra == 'develop'
Requires-Dist: pylint (==2.3.1) ; extra == 'develop'
Requires-Dist: autopep8 (==1.4.3) ; extra == 'develop'
Requires-Dist: m2r (==0.2.1) ; extra == 'develop'
Requires-Dist: ipykernel (==5.1.0) ; extra == 'develop'
Requires-Dist: mkdocs (==1.0.4) ; extra == 'develop'
Requires-Dist: mkdocs-rtd-dropdown (==1.0.2) ; extra == 'develop'
Requires-Dist: tox (==3.7.0) ; extra == 'develop'
Requires-Dist: pre-commit (==1.14.4) ; extra == 'develop'
Requires-Dist: flake8 (==3.7.7) ; extra == 'develop'
Requires-Dist: pytest-cov (==2.6.1) ; extra == 'develop'
